kubestatus/__init__.py
kubestatus/viewer.py
tests/__init__.py
tests/test_viewer.py
kubestatus-0.1.3.dist-info/LICENSE
kubestatus-0.1.3.dist-info/METADATA
kubestatus-0.1.3.dist-info/WHEEL
kubestatus-0.1.3.dist-info/entry_points.txt
kubestatus-0.1.3.dist-info/top_level.txt
kubestatus-0.1.3.dist-info/RECORD
