Metadata-Version: 2.1
Name: kubestatus
Version: 0.1.3
Home-page: https://github.com/ecoenergia/kubestatus.git
Author: Stephen Dictor
Author-email: sdictor@renew-ap.com
License-File: LICENSE
Requires-Dist: rich
